[
  {
    "Date": "2024-03-11",
    "Open": 101.91179136887452,
    "High": 102.73085407926727,
    "Low": 101.05506985979552,
    "Close": 102.63670349121094,
    "Volume": 17577300,
    "outcome": "STRONG_UP",
    "actual_move": 5.164204502290142,
    "time_to_target": 10,
    "target_reached": true,
    "regime": "Sideways"
  },
  {
    "Date": "2024-03-26",
    "Open": 107.94648893182406,
    "High": 108.24775216584004,
    "Low": 106.76967830165512,
    "Close": 107.12742614746094,
    "Volume": 13152300,
    "outcome": "STRONG_UP",
    "actual_move": 7.390798328885312,
    "time_to_target": 10,
    "target_reached": true,
    "regime": "Sideways"
  },
  {
    "Date": "2024-04-10",
    "Open": 114.12238270662203,
    "High": 115.2991932737458,
    "Low": 113.6610749754604,
    "Close": 115.04499816894533,
    "Volume": 17409200,
    "outcome": "DOWN",
    "actual_move": -0.9410725173480942,
    "time_to_target": 10,
    "target_reached": false,
    "regime": "Sideways"
  },
  {
    "Date": "2024-10-03",
    "Open": 116.62616003176664,
    "High": 117.84121195859228,
    "Low": 115.69812462421405,
    "Close": 117.27674102783205,
    "Volume": 16524300,
    "outcome": "DOWN",
    "actual_move": -1.8192265954761002,
    "time_to_target": 10,
    "target_reached": false,
    "regime": "Strong Bull"
  },
  {
    "Date": "2024-11-21",
    "Open": 116.79351943770006,
    "High": 118.2114795760158,
    "Low": 116.01219010802306,
    "Close": 117.6134262084961,
    "Volume": 14675400,
    "outcome": "DOWN",
    "actual_move": -6.8563885674119085,
    "time_to_target": 10,
    "target_reached": false,
    "regime": "Strong Bull"
  },
  {
    "Date": "2025-03-25",
    "Open": 113.312702009722,
    "High": 114.49030456345824,
    "Low": 112.85528460762508,
    "Close": 113.46841430664062,
    "Volume": 12081800,
    "outcome": "DOWN",
    "actual_move": -13.568906760462845,
    "time_to_target": 10,
    "target_reached": false,
    "regime": "Strong Bull"
  },
  {
    "Date": "2025-06-13",
    "Open": 110.34899969163828,
    "High": 110.52579411878652,
    "Low": 108.70874486357586,
    "Close": 110.12310028076172,
    "Volume": 28540200,
    "outcome": "DOWN",
    "actual_move": -3.853012892080569,
    "time_to_target": 10,
    "target_reached": false,
    "regime": "Strong Bull"
  },
  {
    "Date": "2025-08-25",
    "Open": 109.9384128724852,
    "High": 110.94956535698552,
    "Low": 109.5815337454282,
    "Close": 110.77112579345705,
    "Volume": 9744900,
    "outcome": "DOWN",
    "actual_move": -0.9754739877621117,
    "time_to_target": 10,
    "target_reached": false,
    "regime": "Strong Bull"
  },
  {
    "Date": "2026-01-27",
    "Open": 135.25,
    "High": 136.92999267578125,
    "Low": 134.7100067138672,
    "Close": 136.8300018310547,
    "Volume": 14517000,
    "outcome": "STRONG_UP",
    "actual_move": 6.760213313028427,
    "time_to_target": 10,
    "target_reached": true,
    "regime": "Strong Bull"
  }
]